secret_generator/__init__.py
secret_generator/password.py
johanalmquist_secret_generator-0.0.4.dist-info/LICENSE
johanalmquist_secret_generator-0.0.4.dist-info/METADATA
johanalmquist_secret_generator-0.0.4.dist-info/WHEEL
johanalmquist_secret_generator-0.0.4.dist-info/top_level.txt
johanalmquist_secret_generator-0.0.4.dist-info/RECORD
