Metadata-Version: 2.1
Name: johanalmquist-secret-generator
Version: 0.0.4
Summary: A small package with a PasswordGenerator class
Home-page: https://github.com/johanalmquist/secret-generator
Author: Johan Almquist
Author-email: johan.almquist@aranya.se
Project-URL: Bug Tracker, https://github.com/johanalmquist/secret-generator/issues
Project-URL: Changelog, https://github.com/johanalmquist/secret-generator/releases
Classifier: Programming Language :: Python :: 3
Classifier: License :: OSI Approved :: MIT License
Classifier: Operating System :: OS Independent
Requires-Python: >=3.8
License-File: LICENSE
